celpy/__init__.py
celpy/__main__.py
celpy/adapter.py
celpy/c7nlib.py
celpy/cel.lark
celpy/celparser.py
celpy/celtypes.py
celpy/evaluation.py
xlate/__init__.py
xlate/c7n_to_cel.py
scoped_rbac/.permissions.py.swo
scoped_rbac/__init__.py
scoped_rbac/admin.py
scoped_rbac/apps.py
scoped_rbac/authentication.py
scoped_rbac/conf.py
scoped_rbac/filters.py
scoped_rbac/migrations/0001_initial.py
scoped_rbac/migrations/0002_auto_20200219_1405.py
scoped_rbac/migrations/0003_auto_20200223_1846.py
scoped_rbac/migrations/0004_auto_20200223_1921.py
scoped_rbac/migrations/0005_auto_20210104_1614.py
scoped_rbac/migrations/0006_auto_20210608_1254.py
scoped_rbac/migrations/__init__.py
scoped_rbac/models.py
scoped_rbac/permissions.py
scoped_rbac/policy.py
scoped_rbac/rbac_contexts.py
scoped_rbac/registry.py
scoped_rbac/rest.py
scoped_rbac/serializers.py
scoped_rbac/urls.py
django_scoped_rbac-0.7.1.dist-info/LICENSE.txt
django_scoped_rbac-0.7.1.dist-info/LICENSE
django_scoped_rbac-0.7.1.dist-info/WHEEL
django_scoped_rbac-0.7.1.dist-info/METADATA
django_scoped_rbac-0.7.1.dist-info/RECORD
